_datalad_buildsupport/__init__.py
_datalad_buildsupport/formatters.py
_datalad_buildsupport/setup.py
datalad_lgpdextension/__init__.py
datalad_lgpdextension/_version.py
datalad_lgpdextension/lgpd_extension.py
datalad_lgpdextension/main.py
datalad_lgpdextension/crypto/__init__.py
datalad_lgpdextension/crypto/rsa.py
datalad_lgpdextension/runner/__init__.py
datalad_lgpdextension/runner/actions.py
datalad_lgpdextension/runner/operations.py
datalad_lgpdextension/tests/__init__.py
datalad_lgpdextension/tests/test_controller.py
datalad_lgpdextension/tests/test_main.py
datalad_lgpdextension/tests/test_register.py
datalad_lgpdextension/tests/crypto/__init__.py
datalad_lgpdextension/tests/crypto/rsa.py
datalad_lgpdextension/tests/runner/__init__.py
datalad_lgpdextension/tests/runner/actions.py
datalad_lgpdextension/tests/runner/operations.py
datalad_lgpdextension/tests/utils/__init__.py
datalad_lgpdextension/tests/utils/dataframe.py
datalad_lgpdextension/tests/utils/folder.py
datalad_lgpdextension/tests/writers/__init__.py
datalad_lgpdextension/tests/writers/csv.py
datalad_lgpdextension/tests/writers/dataframe.py
datalad_lgpdextension/tests/writers/parquet.py
datalad_lgpdextension/utils/__init__.py
datalad_lgpdextension/utils/dataframe.py
datalad_lgpdextension/utils/folder.py
datalad_lgpdextension/utils/generate_config.py
datalad_lgpdextension/writers/__init__.py
datalad_lgpdextension/writers/csv.py
datalad_lgpdextension/writers/dataframe.py
datalad_lgpdextension/writers/parquet.py
datalad_lgpdextension-0.5.0.dist-info/LICENSE
datalad_lgpdextension-0.5.0.dist-info/METADATA
datalad_lgpdextension-0.5.0.dist-info/WHEEL
datalad_lgpdextension-0.5.0.dist-info/entry_points.txt
datalad_lgpdextension-0.5.0.dist-info/top_level.txt
datalad_lgpdextension-0.5.0.dist-info/RECORD
