Metadata-Version: 2.1
Name: datalad-lgpdextension
Version: 0.5.0
Summary: Datalad extension to apply lgpd patterns
Home-page: https://github.com/messiasoliveira/lgpdextension-datalad.git
Download-URL: https://github.com/messiasoliveira/lgpdextension-datalad/archive/refs/tags/version.tar.gz
Author: Messias Silva
Author-email: messias.oliveira2011@hotmail.com
License: MIT
Keywords: lgpd,datalad,extension
Classifier: Programming Language :: Python
Classifier: License :: OSI Approved :: BSD License
Classifier: Programming Language :: Python :: 3
Requires-Python: >=3.5
License-File: LICENSE
Requires-Dist: datalad (>=0.12.0)
Requires-Dist: rsa (>=4.8)
Requires-Dist: pandas (>=1.4.1)
Requires-Dist: fastparquet (>=0.8.0)
Provides-Extra: devel
Requires-Dist: nose ; extra == 'devel'
Requires-Dist: coverage ; extra == 'devel'
Requires-Dist: pandas ; extra == 'devel'
Requires-Dist: rsa ; extra == 'devel'
Requires-Dist: fastparquet ; extra == 'devel'
